./.env.example
./.gitignore
./Dockerfile
./LICENSE
./PKG-INFO
./README.md
./pyproject.toml
./server.py
./uv.lock
./.amazonq/rules/guidelines.md
./deploy/README.md
./deploy/build-and-push.sh
./deploy/publish-pypi.sh
./helm-chart/Chart.yaml
./helm-chart/values.yaml
./helm-chart/templates/_helpers.tpl
./helm-chart/templates/deployment.yaml
./helm-chart/templates/secret.yaml
./mcp-clients/claude-desktop-config.json
./mcp-clients/claude-desktop-local.json
./mcp-clients/cline-config.json
./mcp-clients/continue-config.json
./mcp-clients/vscode-user-settings.json
./mcp-clients/vscode-workspace-settings.json
./references/FastMCP_2.0_Changelog.md
./references/FastMCP_2.0_Overview.md
./references/README.md
./test/QUALITATIVE_TEST_GUIDE.md
./test/QUALITATIVE_TEST_RESULTS.md
./test/TEST_GUIDE.md
./test/comprehensive_real_tests.py
./test/content_validation_tests.py
./test/jira_integration_tests.py
./test/real_content_tests.py
./test/test_suite.py
jira_mcp_standalone-2.0.0.dist-info/METADATA
jira_mcp_standalone-2.0.0.dist-info/WHEEL
jira_mcp_standalone-2.0.0.dist-info/entry_points.txt
jira_mcp_standalone-2.0.0.dist-info/licenses/LICENSE
jira_mcp_standalone-2.0.0.dist-info/RECORD
