Metadata-Version: 2.4
Name: jira-mcp-standalone
Version: 2.0.0
Summary: JIRA MCP Server - FastMCP 2.0 implementation with 47 tools for AI integration
Project-URL: Homepage, https://github.com/yourusername/jira-mcp-server
Project-URL: Repository, https://github.com/yourusername/jira-mcp-server.git
Project-URL: Issues, https://github.com/yourusername/jira-mcp-server/issues
Project-URL: Documentation, https://github.com/yourusername/jira-mcp-server#readme
Author-email: Roy Ashish <royashish@gmail.com>
License: MIT
License-File: LICENSE
Keywords: ai,atlassian,jira,mcp,model-context-protocol
Classifier: Development Status :: 5 - Production/Stable
Classifier: Intended Audience :: Developers
Classifier: License :: OSI Approved :: MIT License
Classifier: Programming Language :: Python :: 3
Classifier: Programming Language :: Python :: 3.10
Classifier: Programming Language :: Python :: 3.11
Classifier: Programming Language :: Python :: 3.12
Classifier: Topic :: Internet :: WWW/HTTP :: HTTP Servers
Classifier: Topic :: Software Development :: Libraries :: Python Modules
Requires-Python: >=3.10
Requires-Dist: fastmcp>=2.0.0
Requires-Dist: python-dotenv>=1.0.0
Requires-Dist: requests>=2.25.0
Provides-Extra: dev
Requires-Dist: black>=23.0.0; extra == 'dev'
Requires-Dist: isort>=5.12.0; extra == 'dev'
Requires-Dist: mypy>=1.5.0; extra == 'dev'
Requires-Dist: pre-commit>=3.0.0; extra == 'dev'
Provides-Extra: test
Requires-Dist: pytest-asyncio>=0.21.0; extra == 'test'
Requires-Dist: pytest-cov>=4.0.0; extra == 'test'
Requires-Dist: pytest>=7.0.0; extra == 'test'
